<?xml version="1.0" encoding="utf-8" ?><dwsync><file name="Overhead.jpg" server="ftp.jacovip.com" local="3660936788" remote="3659514840" Dst="-1" /><file name="Pool6.jpg" server="ftp.jacovip.com" local="3441400486" remote="323953104486545564" Dst="-1" /><file name="BachelorPartyGroup.jpg" server="ftp.jacovip.com" local="3455369700" remote="323953104486545564" Dst="-1" /><file name="PoolGroup.jpg" server="ftp.jacovip.com" local="3455369742" remote="323953104486545564" Dst="-1" /><file name="WeddingCeremony.jpg" server="ftp.jacovip.com" local="3455376037" remote="323953104486545564" Dst="-1" /><file name="DinnerTime.jpg" server="ftp.jacovip.com" local="3455376050" remote="323953104486545564" Dst="-1" /><file name="CasaBlancaWide.jpg" server="ftp.jacovip.com" local="3426104490" remote="323953104486545564" Dst="-1" /><file name="Pool7.jpg" server="ftp.jacovip.com" local="3441400537" remote="323953104486545564" Dst="-1" /><file name="Pool9.jpg" server="ftp.jacovip.com" local="3441400572" remote="323953104486545564" Dst="-1" /><file name="NewJacuzzi2Pic3.jpg" server="ftp.jacovip.com" local="3380069393" remote="323953104387508784" Dst="-1" /><file name="1Beachfront.jpg" server="ftp.jacovip.com" local="3392682219" remote="323953104486545564" Dst="-1" /><file name="2Pools2.jpg" server="ftp.jacovip.com" local="3441400620" remote="323953104387508784" Dst="-1" /><file name="Pool11.jpg" server="ftp.jacovip.com" local="3441400681" remote="323953104387508784" Dst="-1" /><file name="Pool8.jpg" server="ftp.jacovip.com" local="3441400553" remote="323953104486545564" Dst="-1" /><file name="2DeckView.jpg" server="ftp.jacovip.com" local="3392681734" remote="323953104486545564" Dst="-1" /><file name="BalconyView.jpg" server="ftp.jacovip.com" local="3441400709" remote="323953104486545564" Dst="-1" /><file name="WeddingGroup.jpg" server="ftp.jacovip.com" local="3416812228" remote="323953104486545564" Dst="-1" /><file name="WeddingSetup2.jpg" server="ftp.jacovip.com" local="3441399680" remote="323953104486545564" Dst="-1" /><file name="WeddingSetup.jpg" server="ftp.jacovip.com" local="3441399408" remote="323953104387508784" Dst="-1" /><file name="RanchoPoolTable22.jpg" server="ftp.jacovip.com" local="3471223944" remote="323953104486545564" Dst="-1" /><file name="Rancho22.jpg" server="ftp.jacovip.com" local="3471223925" remote="323953104486545564" Dst="-1" /><file name="Pool3.jpg" server="ftp.jacovip.com" local="3441399788" remote="323953104486545564" Dst="-1" /><file name="NewRancho1.jpg" server="ftp.jacovip.com" local="3380069063" remote="323953104387508784" Dst="-1" /><file name="1Rancho.jpg" server="ftp.jacovip.com" local="3392681192" remote="323953104486545264" Dst="-1" /><file name="RanchoSunset.jpg" server="ftp.jacovip.com" local="3367839725" remote="323953104486545564" Dst="-1" /><file name="Seating.jpg" server="ftp.jacovip.com" local="3441399940" remote="323953104387508784" Dst="-1" /><file name="Pool1.jpg" server="ftp.jacovip.com" local="3441399928" remote="323953104387508844" Dst="-1" /><file name="LivingRoom22.jpg" server="ftp.jacovip.com" local="3471223645" remote="323953104387508844" Dst="-1" /><file name="LivingRoom23.jpg" server="ftp.jacovip.com" local="3471223656" remote="323953104387508844" Dst="-1" /><file name="LivingRoom24.jpg" server="ftp.jacovip.com" local="3471223665" remote="323953104387508844" Dst="-1" /><file name="LivingRoom25.jpg" server="ftp.jacovip.com" local="3471223673" remote="323953104387508844" Dst="-1" /><file name="Kitchen2.jpg" server="ftp.jacovip.com" local="3471223628" remote="323953104387508844" Dst="-1" /><file name="Kitchen3.jpg" server="ftp.jacovip.com" local="3570271055" remote="323953104486545564" Dst="-1" /><file name="EnterLiving.jpg" server="ftp.jacovip.com" local="3441400443" remote="323953104387508844" Dst="-1" /><file name="OutFront.jpg" server="ftp.jacovip.com" local="3441399959" remote="323953104387508844" Dst="-1" /><file name="DiningTable22.jpg" server="ftp.jacovip.com" local="3471223682" remote="323953104387508844" Dst="-1" /><file name="1Dining.jpg" server="ftp.jacovip.com" local="3392679697" remote="323953104486545264" Dst="-1" /><file name="DiningTable23.jpg" server="ftp.jacovip.com" local="3471223692" remote="323953104387508844" Dst="-1" /><file name="DiningTable24.jpg" server="ftp.jacovip.com" local="3471223700" remote="323953104387508844" Dst="-1" /><file name="2Dining.jpg" server="ftp.jacovip.com" local="3392679720" remote="323953104387508844" Dst="-1" /><file name="OceanView22.jpg" server="ftp.jacovip.com" local="3471223603" remote="323953104387508844" Dst="-1" /><file name="3Guys.jpg" server="ftp.jacovip.com" local="3441399458" remote="323953104486545564" Dst="-1" /><file name="MidnightSnack.jpg" server="ftp.jacovip.com" local="3436907194" remote="323953104486545564" Dst="-1" /><file name="Kitchen20.jpg" server="ftp.jacovip.com" local="3471251388" remote="323953104387508844" Dst="-1" /><file name="Kitchen21.jpg" server="ftp.jacovip.com" local="3471251408" remote="323953104387508844" Dst="-1" /><file name="2Pools.jpg" server="ftp.jacovip.com" local="3441399907" remote="323953104387508844" Dst="-1" /><file name="Pool4.jpg" server="ftp.jacovip.com" local="3570277556" remote="323953104486545624" Dst="-1" /><file name="OceanView23.jpg" server="ftp.jacovip.com" local="3471223900" remote="323953104486545564" Dst="-1" /><file name="OceanView24.jpg" server="ftp.jacovip.com" local="3471223908" remote="323953104486545564" Dst="-1" /><file name="OceanView25.jpg" server="ftp.jacovip.com" local="3471223918" remote="323953104486545624" Dst="-1" /><file name="Bathroom.jpg" server="ftp.jacovip.com" local="3367838071" remote="323953104387508904" Dst="-1" /><file name="CommonArea22.jpg" server="ftp.jacovip.com" local="3471223733" remote="323953104387508904" Dst="-1" /><file name="1DeckView.jpg" server="ftp.jacovip.com" local="3392681624" remote="323953104486545264" Dst="-1" /><file name="NewBathroomPic2.jpg" server="ftp.jacovip.com" local="3380069153" remote="323953104486545684" Dst="-1" /><file name="NewJacuzzi3.jpg" server="ftp.jacovip.com" local="3380069217" remote="323953104486545624" Dst="-1" /><file name="NewBedroom11Pic1.jpg" server="ftp.jacovip.com" local="3380069129" remote="323953104387508904" Dst="-1" /><file name="RiverView3.jpg" server="ftp.jacovip.com" local="3441400661" remote="323953104387508904" Dst="-1" /><file name="RiverView2.jpg" server="ftp.jacovip.com" local="3441399843" remote="323953104387508904" Dst="-1" /><file name="RiverSeating.jpg" server="ftp.jacovip.com" local="3441399810" remote="323953104387508904" Dst="-1" /><file name="RiverView.jpg" server="ftp.jacovip.com" local="3441399825" remote="323953104387508904" Dst="-1" /><file name="Pool5.jpg" server="ftp.jacovip.com" local="3441400469" remote="323953104486545684" Dst="-1" /><file name="Pool10.jpg" server="ftp.jacovip.com" local="3441400592" remote="323953104486545684" Dst="-1" /><file name="NewSunset1.jpg" server="ftp.jacovip.com" local="3380069323" remote="323953104486545684" Dst="-1" /><file name="RanchoDJ.jpg" server="ftp.jacovip.com" local="3489229637" remote="323953104486545564" Dst="-1" /><file name="CasaBlancaGroup.jpg" server="ftp.jacovip.com" local="3489233285" remote="323953104486545564" Dst="-1" /><file name=".DS_Store" server="ftp.jacovip.com" local="3471251344" remote="323953104486545264" Dst="-1" /><file name="1BeachExit.jpg" server="ftp.jacovip.com" local="3392682034" remote="323953104486545264" Dst="-1" /><file name="1GuardHouseEntrance.jpg" server="ftp.jacovip.com" local="3392681390" remote="323953104486545564" Dst="-1" /><file name="1LargeYard.jpg" server="ftp.jacovip.com" local="3392681836" remote="323953104486545264" Dst="-1" /><file name="1Living.jpg" server="ftp.jacovip.com" local="3392679682" remote="323953104486545264" Dst="-1" /><file name="1Kitchen.jpg" server="ftp.jacovip.com" local="3392679665" remote="323953104486545264" Dst="-1" /><file name="1Pool.jpg" server="ftp.jacovip.com" local="3392681288" remote="323953104486545264" Dst="-1" /><file name="1View.jpg" server="ftp.jacovip.com" local="3392681924" remote="323953104486545264" Dst="-1" /><file name="1Yard.jpg" server="ftp.jacovip.com" local="3392680972" remote="323953104486545264" Dst="-1" /><file name="2View.jpg" server="ftp.jacovip.com" local="3392682120" remote="323953104486545264" Dst="-1" /><file name="2Yard.jpg" server="ftp.jacovip.com" local="3392681529" remote="323953104486545264" Dst="-1" /><file name="4DayView2.jpg" server="ftp.jacovip.com" local="3392680816" remote="323953104486545264" Dst="-1" /><file name="4DayView.jpg" server="ftp.jacovip.com" local="3392680693" remote="323953104486545264" Dst="-1" /><file name="Balcony-10.jpg" server="ftp.jacovip.com" local="3570269317" remote="323953104486545264" Dst="-1" /><file name="Balcony-11.jpg" server="ftp.jacovip.com" local="3570271695" remote="323953104486545564" Dst="-1" /><file name="Balcony-2.jpg" server="ftp.jacovip.com" local="3570269207" remote="323953104486545564" Dst="-1" /><file name="Balcony-3.jpg" server="ftp.jacovip.com" local="3570269226" remote="323953104486545264" Dst="-1" /><file name="Balcony-4.jpg" server="ftp.jacovip.com" local="3570269243" remote="323953104486545564" Dst="-1" /><file name="Balcony-5.jpg" server="ftp.jacovip.com" local="3570269265" remote="323953104486545264" Dst="-1" /><file name="Balcony-6.jpg" server="ftp.jacovip.com" local="3570269278" remote="323953104486545264" Dst="-1" /><file name="Balcony-7.jpg" server="ftp.jacovip.com" local="3570269288" remote="323953104486545684" Dst="-1" /><file name="Balcony-8.jpg" server="ftp.jacovip.com" local="3570269297" remote="323953104486545624" Dst="-1" /><file name="Balcony-9.jpg" server="ftp.jacovip.com" local="3570269306" remote="323953104486545624" Dst="-1" /><file name="Bathroom13-2.jpg" server="ftp.jacovip.com" local="3570271590" remote="323953104486545624" Dst="-1" /><file name="Bathroom13.jpg" server="ftp.jacovip.com" local="3570271558" remote="323953104486545624" Dst="-1" /><file name="Bathroom3-1.jpg" server="ftp.jacovip.com" local="3570266249" remote="323953104486545624" Dst="-1" /><file name="Bathroom3-2.jpg" server="ftp.jacovip.com" local="3570266267" remote="323953104486545624" Dst="-1" /><file name="Bathroom5.jpg" server="ftp.jacovip.com" local="3570267868" remote="323953104486545624" Dst="-1" /><file name="Bathroom6.jpg" server="ftp.jacovip.com" local="3570267971" remote="323953104486545624" Dst="-1" /><file name="Bathroom7.jpg" server="ftp.jacovip.com" local="3570268140" remote="323953104486545624" Dst="-1" /><file name="Bedroom.jpg" server="ftp.jacovip.com" local="3367840147" remote="323953104486545324" Dst="-1" /><file name="Bedroom1-1.jpg" server="ftp.jacovip.com" local="3570267037" remote="323953104486545564" Dst="-1" /><file name="Bedroom1-2.jpg" server="ftp.jacovip.com" local="3570267127" remote="323953104486545564" Dst="-1" /><file name="Bedroom1-3.jpg" server="ftp.jacovip.com" local="3570267189" remote="323953104486545324" Dst="-1" /><file name="Bedroom1-4.jpg" server="ftp.jacovip.com" local="3570267390" remote="323953104486545324" Dst="-1" /><file name="Bedroom1-5.jpg" server="ftp.jacovip.com" local="3570267445" remote="323953104486545564" Dst="-1" /><file name="Bedroom1-6.jpg" server="ftp.jacovip.com" local="3570267486" remote="323953104486545564" Dst="-1" /><file name="Bedroom10-1.jpg" server="ftp.jacovip.com" local="3570268667" remote="323953104486545624" Dst="-1" /><file name="Bedroom10-2.jpg" server="ftp.jacovip.com" local="3570268780" remote="323953104486545624" Dst="-1" /><file name="Bedroom10-4.jpg" server="ftp.jacovip.com" local="3570268938" remote="323953104486545624" Dst="-1" /><file name="Bedroom10-3.jpg" server="ftp.jacovip.com" local="3570268899" remote="323953104486545624" Dst="-1" /><file name="Bedroom11-2.jpg" server="ftp.jacovip.com" local="3570269138" remote="323953104486545624" Dst="-1" /><file name="Bedroom11-3.jpg" server="ftp.jacovip.com" local="3570269155" remote="323953104486545624" Dst="-1" /><file name="Bedroom11-1.jpg" server="ftp.jacovip.com" local="3570269084" remote="323953104486545624" Dst="-1" /><file name="Bedroom11-4.jpg" server="ftp.jacovip.com" local="3570269175" remote="323953104486545624" Dst="-1" /><file name="Bedroom12-1.jpg" server="ftp.jacovip.com" local="3570271104" remote="323953104486545324" Dst="-1" /><file name="Bedroom12-2.jpg" server="ftp.jacovip.com" local="3570271125" remote="323953104486545624" Dst="-1" /><file name="Bedroom12-3.jpg" server="ftp.jacovip.com" local="3570271141" remote="323953104486545624" Dst="-1" /><file name="Bedroom12-4.jpg" server="ftp.jacovip.com" local="3570271212" remote="323953104486545624" Dst="-1" /><file name="Bedroom12-5.jpg" server="ftp.jacovip.com" local="3570271299" remote="323953104486545624" Dst="-1" /><file name="Bedroom13-3.jpg" server="ftp.jacovip.com" local="3570271391" remote="323953104486545624" Dst="-1" /><file name="Bedroom13-2.jpg" server="ftp.jacovip.com" local="3570271345" remote="323953104486545624" Dst="-1" /><file name="Bedroom13-1.jpg" server="ftp.jacovip.com" local="3570271326" remote="323953104486545324" Dst="-1" /><file name="Bedroom13-4.jpg" server="ftp.jacovip.com" local="3570271448" remote="323953104486545624" Dst="-1" /><file name="Bedroom13-5.jpg" server="ftp.jacovip.com" local="3570271490" remote="323953104486545324" Dst="-1" /><file name="Bedroom14-1.jpg" server="ftp.jacovip.com" local="3570271611" remote="323953104486545624" Dst="-1" /><file name="Bedroom14-2.jpg" server="ftp.jacovip.com" local="3570271628" remote="323953104486545624" Dst="-1" /><file name="Bedroom14-3.jpg" server="ftp.jacovip.com" local="3570271657" remote="323953104486545624" Dst="-1" /><file name="Bedroom14-4.jpg" server="ftp.jacovip.com" local="3570271673" remote="323953104486545624" Dst="-1" /><file name="Bedroom2-1.jpg" server="ftp.jacovip.com" local="3570266548" remote="323953104486545624" Dst="-1" /><file name="Bedroom2-2.jpg" server="ftp.jacovip.com" local="3570266676" remote="323953104486545324" Dst="-1" /><file name="Bedroom2-3.jpg" server="ftp.jacovip.com" local="3570266861" remote="323953104486545624" Dst="-1" /><file name="Bedroom2-4.jpg" server="ftp.jacovip.com" local="3570266893" remote="323953104486545624" Dst="-1" /><file name="Bedroom2-5.jpg" server="ftp.jacovip.com" local="3570266925" remote="323953104486545624" Dst="-1" /><file name="Bedroom2.jpg" server="ftp.jacovip.com" local="3367838122" remote="323953104486545324" Dst="-1" /><file name="Bedroom3-1.jpg" server="ftp.jacovip.com" local="3570265781" remote="323953104486545624" Dst="-1" /><file name="Bedroom3-2.jpg" server="ftp.jacovip.com" local="3570265855" remote="323953104486545624" Dst="-1" /><file name="Bedroom3-3.jpg" server="ftp.jacovip.com" local="3570265879" remote="323953104486545624" Dst="-1" /><file name="Bedroom3-4.jpg" server="ftp.jacovip.com" local="3570266186" remote="323953104486545624" Dst="-1" /><file name="Bedroom3-5.jpg" server="ftp.jacovip.com" local="3570266464" remote="323953104486545624" Dst="-1" /><file name="Bedroom3-6.jpg" server="ftp.jacovip.com" local="3570269394" remote="323953104486545324" Dst="-1" /><file name="Bedroom3.jpg" server="ftp.jacovip.com" local="3367838081" remote="323953104486545324" Dst="-1" /><file name="Bedroom4-1.jpg" server="ftp.jacovip.com" local="3570267538" remote="323953104486545624" Dst="-1" /><file name="Bedroom4-2.jpg" server="ftp.jacovip.com" local="3570267559" remote="323953104486545324" Dst="-1" /><file name="Bedroom4-3.jpg" server="ftp.jacovip.com" local="3570267571" remote="323953104486545624" Dst="-1" /><file name="Bedroom4-4.jpg" server="ftp.jacovip.com" local="3570267583" remote="323953104486545624" Dst="-1" /><file name="Bedroom4-5.jpg" server="ftp.jacovip.com" local="3570267605" remote="323953104486545324" Dst="-1" /><file name="Bedroom5-1.jpg" server="ftp.jacovip.com" local="3570267676" remote="323953104486545624" Dst="-1" /><file name="Bedroom4-6.jpg" server="ftp.jacovip.com" local="3570267649" remote="323953104486545624" Dst="-1" /><file name="Bedroom4.jpg" server="ftp.jacovip.com" local="3367838132" remote="323953104486545324" Dst="-1" /><file name="Bedroom5-2.jpg" server="ftp.jacovip.com" local="3570267754" remote="323953104486545624" Dst="-1" /><file name="Bedroom5-3.jpg" server="ftp.jacovip.com" local="3570267773" remote="323953104486545624" Dst="-1" /><file name="Bedroom5-4.jpg" server="ftp.jacovip.com" local="3570267850" remote="323953104486545324" Dst="-1" /><file name="Bedroom51.jpg" server="ftp.jacovip.com" local="3471223533" remote="323953104486545324" Dst="-1" /><file name="Bedroom5.jpg" server="ftp.jacovip.com" local="3367838061" remote="323953104486545324" Dst="-1" /><file name="Bedroom6-1.jpg" server="ftp.jacovip.com" local="3570267898" remote="323953104486545624" Dst="-1" /><file name="Bedroom6-2.jpg" server="ftp.jacovip.com" local="3570267915" remote="323953104486545624" Dst="-1" /><file name="Bedroom6-3.jpg" server="ftp.jacovip.com" local="3570267933" remote="323953104486545624" Dst="-1" /><file name="Bedroom6-4.jpg" server="ftp.jacovip.com" local="3570267950" remote="323953104486545324" Dst="-1" /><file name="Bedroom6.jpg" server="ftp.jacovip.com" local="3367838045" remote="323953104486545324" Dst="-1" /><file name="Bedroom7-1.jpg" server="ftp.jacovip.com" local="3570268109" remote="323953104486545324" Dst="-1" /><file name="Bedroom7-2.jpg" server="ftp.jacovip.com" local="3570268166" remote="323953104486545324" Dst="-1" /><file name="Bedroom7-3.jpg" server="ftp.jacovip.com" local="3570268181" remote="323953104486545624" Dst="-1" /><file name="Bedroom7-4.jpg" server="ftp.jacovip.com" local="3570268198" remote="323953104486545624" Dst="-1" /><file name="Bedroom7-5.jpg" server="ftp.jacovip.com" local="3570268226" remote="323953104486545624" Dst="-1" /><file name="Bedroom8-2.jpg" server="ftp.jacovip.com" local="3570268452" remote="323953104486545624" Dst="-1" /><file name="Bedroom8-1.jpg" server="ftp.jacovip.com" local="3570268406" remote="323953104486545624" Dst="-1" /><file name="Bedroom7.jpg" server="ftp.jacovip.com" local="3367837909" remote="323953104486545324" Dst="-1" /><file name="Bedroom8-3.jpg" server="ftp.jacovip.com" local="3570268482" remote="323953104486545624" Dst="-1" /><file name="Bedroom9-1.jpg" server="ftp.jacovip.com" local="3570268498" remote="323953104486545624" Dst="-1" /><file name="Bedroom8.jpg" server="ftp.jacovip.com" local="3367837898" remote="323953104486545324" Dst="-1" /><file name="Bedroom9-2.jpg" server="ftp.jacovip.com" local="3570268512" remote="323953104486545624" Dst="-1" /><file name="Bedroom9-3.jpg" server="ftp.jacovip.com" local="3570268609" remote="323953104486545624" Dst="-1" /><file name="Bedroom9.jpg" server="ftp.jacovip.com" local="3367837841" remote="323953104486545324" Dst="-1" /><file name="CasaPlayaGrandeEvening.jpg" server="ftp.jacovip.com" local="3367837779" remote="323953104486545384" Dst="-1" /><file name="CasaPlayaGrandeNightView.jpg" server="ftp.jacovip.com" local="3367837822" remote="323953104486545384" Dst="-1" /><file name="DayView2Front.jpg" server="ftp.jacovip.com" local="3392674457" remote="323953104486545384" Dst="-1" /><file name="DayView3Front.jpg" server="ftp.jacovip.com" local="3392674495" remote="323953104486545384" Dst="-1" /><file name="Exterior1.jpg" server="ftp.jacovip.com" local="3570265697" remote="323953104486545384" Dst="-1" /><file name="DayViewFront.jpg" server="ftp.jacovip.com" local="3424048037" remote="323953104486545384" Dst="-1" /><file name="FineArt.jpg" server="ftp.jacovip.com" local="3367837941" remote="323953104486545384" Dst="-1" /><file name="Jacuzzi2-1.jpg" server="ftp.jacovip.com" local="3570268244" remote="323953104486545624" Dst="-1" /><file name="Jacuzzi2-2.jpg" server="ftp.jacovip.com" local="3570268255" remote="323953104486548324" Dst="-1" /><file name="Jacuzzi2Pic2.jpg" server="ftp.jacovip.com" local="3380069298" remote="323953104486545384" Dst="-1" /><file name="JacuzziDeck.jpg" server="ftp.jacovip.com" local="3367838151" remote="323953104486545384" Dst="-1" /><file name="JacuzziView.jpg" server="ftp.jacovip.com" local="3367839681" remote="323953104486545384" Dst="-1" /><file name="Kitchen1-1.jpg" server="ftp.jacovip.com" local="3367837953" remote="323953104486545384" Dst="-1" /><file name="Kitchen1-2.jpg" server="ftp.jacovip.com" local="3367837963" remote="323953104486545384" Dst="-1" /><file name="Kitchen1.jpg" server="ftp.jacovip.com" local="3570271079" remote="323953104486545564" Dst="-1" /><file name="Kitchen4.jpg" server="ftp.jacovip.com" local="3570271035" remote="323953104486545564" Dst="-1" /><file name="LivingRoom1.jpg" server="ftp.jacovip.com" local="3570270782" remote="323953104486545564" Dst="-1" /><file name="LivingRoom.jpg" server="ftp.jacovip.com" local="3367840195" remote="323953104486545384" Dst="-1" /><file name="LivingRoom10.jpg" server="ftp.jacovip.com" local="3570270958" remote="323953104486545384" Dst="-1" /><file name="LivingRoom3.jpg" server="ftp.jacovip.com" local="3570270852" remote="323953104486545564" Dst="-1" /><file name="LivingRoom11.jpg" server="ftp.jacovip.com" local="3570270984" remote="323953104486545564" Dst="-1" /><file name="LivingRoom2.jpg" server="ftp.jacovip.com" local="3570270833" remote="323953104486545384" Dst="-1" /><file name="LivingRoom4.jpg" server="ftp.jacovip.com" local="3570270866" remote="323953104486545384" Dst="-1" /><file name="LivingRoom5.jpg" server="ftp.jacovip.com" local="3570270884" remote="323953104486545564" Dst="-1" /><file name="LivingRoom6.jpg" server="ftp.jacovip.com" local="3570270908" remote="323953104486545384" Dst="-1" /><file name="LivingRoom7.jpg" server="ftp.jacovip.com" local="3570270923" remote="323953104486545564" Dst="-1" /><file name="LivingRoom8.jpg" server="ftp.jacovip.com" local="3570270936" remote="323953104486545384" Dst="-1" /><file name="LivingRoom9.jpg" server="ftp.jacovip.com" local="3570270946" remote="323953104486545564" Dst="-1" /><file name="Massage.jpg" server="ftp.jacovip.com" local="3441400633" remote="323953104486545384" Dst="-1" /><file name="MasterBalcony.jpg" server="ftp.jacovip.com" local="3367837975" remote="323953104486545384" Dst="-1" /><file name="NewBalconySunset2.jpg" server="ftp.jacovip.com" local="3380069310" remote="323953104486545384" Dst="-1" /><file name="NewBalconySunset3.jpg" server="ftp.jacovip.com" local="3424047548" remote="323953104486545384" Dst="-1" /><file name="NewBalconySunsetView.jpg" server="ftp.jacovip.com" local="3380069107" remote="323953104486545384" Dst="-1" /><file name="NewBedroom11Pic2.jpg" server="ftp.jacovip.com" local="3380069165" remote="323953104486545384" Dst="-1" /><file name="NewBedroom11Pic3.jpg" server="ftp.jacovip.com" local="3380069228" remote="323953104486545384" Dst="-1" /><file name="NewBedroom11Pic4.jpg" server="ftp.jacovip.com" local="3380069238" remote="323953104486545384" Dst="-1" /><file name="NewBedroomPic2.jpg" server="ftp.jacovip.com" local="3380069018" remote="323953104486545384" Dst="-1" /><file name="NewBedroomPic1.jpg" server="ftp.jacovip.com" local="3380068966" remote="323953104486545384" Dst="-1" /><file name="NewBedroomPic5.jpg" server="ftp.jacovip.com" local="3380069423" remote="323953104486545384" Dst="-1" /><file name="NewBedroomPic6.jpg" server="ftp.jacovip.com" local="3380069434" remote="323953104486545384" Dst="-1" /><file name="NewBedroomPic7.jpg" server="ftp.jacovip.com" local="3380069443" remote="323953104486545384" Dst="-1" /><file name="NewCLoseUp.jpg" server="ftp.jacovip.com" local="3367838002" remote="323953104486545384" Dst="-1" /><file name="Staircase.jpg" server="ftp.jacovip.com" local="3570269343" remote="323953104486545624" Dst="-1" /><file name="CasaBlancaGroup4.jpg" server="ftp.jacovip.com" local="3601164806" remote="326240088703205244" Dst="-1" /><file name="GroupWith-VIP-Concierges3.jpg" server="ftp.jacovip.com" local="3601164736" remote="326240088703205244" Dst="-1" /><file name="CasaBlancaBachelorParty.jpg" server="ftp.jacovip.com" local="3601164096" remote="326240088703205244" Dst="-1" /><file name="CasaBlancaGroup3.jpg" server="ftp.jacovip.com" local="3601164560" remote="326240088703205244" Dst="-1" /><file name="CasaBlancaDailyDriver.jpg" server="ftp.jacovip.com" local="3601164205" remote="326240088703205244" Dst="-1" /><file name="JacoTransportationService.jpg" server="ftp.jacovip.com" local="3601164678" remote="326240088703205244" Dst="-1" /><file name="JacoBachelorPartyConcierge.jpg" server="ftp.jacovip.com" local="3601164024" remote="326240088703205244" Dst="-1" /><file name="BachelorPartyDailyDriver.jpg" server="ftp.jacovip.com" local="3601164003" remote="326240088703205244" Dst="-1" /><file name="CasaBlancaRanchoConcierge.jpg" server="ftp.jacovip.com" local="3601164696" remote="326240088703205244" Dst="-1" /><file name="GroupWithConcierges.jpg" server="ftp.jacovip.com" local="3601164174" remote="326240088703205244" Dst="-1" /><file name="JacoBeach-DJ-Service.jpg" server="ftp.jacovip.com" local="3601164646" remote="326240088703205244" Dst="-1" /><file name="BachelorPartyNight.jpg" server="ftp.jacovip.com" local="3601164781" remote="326240088703205244" Dst="-1" /><file name="CheckOutDay.jpg" server="ftp.jacovip.com" local="3601164155" remote="326240088703205244" Dst="-1" /><file name="CasaBlancaGroup2.jpg" server="ftp.jacovip.com" local="3601165082" remote="326240088703205244" Dst="-1" /><file name="JacoBeach-Chef-Service.jpg" server="ftp.jacovip.com" local="3601164660" remote="326240088703205244" Dst="-1" /><file name="Jaco-VIP-Chef-Service.jpg" server="ftp.jacovip.com" local="3601164333" remote="326240088703205244" Dst="-1" /><file name="CasaBlancaChefService.jpg" server="ftp.jacovip.com" local="3601164628" remote="326240088703205244" Dst="-1" /><file name="GroupWithChef2.jpg" server="ftp.jacovip.com" local="3601164503" remote="326240088703205244" Dst="-1" /><file name="GroupWithChef.jpg" server="ftp.jacovip.com" local="3601164486" remote="326240088703205244" Dst="-1" /><file name="BirthdayCake.jpg" server="ftp.jacovip.com" local="3601164348" remote="326240088703205244" Dst="-1" /><file name="GroupChefService.jpg" server="ftp.jacovip.com" local="3601163984" remote="326240088703205244" Dst="-1" /><file name="JacoVIP-Concierge.jpg" server="ftp.jacovip.com" local="3601164133" remote="326240088703205244" Dst="-1" /><file name="GroupWigs.jpg" server="ftp.jacovip.com" local="3601164225" remote="326240088703205244" Dst="-1" /><file name="JacoMassage.jpg" server="ftp.jacovip.com" local="3601163961" remote="326240088703205244" Dst="-1" /><file name="Jaco-VIP-Concierge2.jpg" server="ftp.jacovip.com" local="3601164758" remote="326240088703205244" Dst="-1" /><file name="Jaco-VIP-Concierge.jpg" server="ftp.jacovip.com" local="3601164253" remote="326240088703205244" Dst="-1" /><file name="JacoVIP-Concierges2.jpg" server="ftp.jacovip.com" local="3601164612" remote="326240088703205244" Dst="-1" /><file name="JacoVIP-Concierges.jpg" server="ftp.jacovip.com" local="3601164597" remote="326240088703205244" Dst="-1" /><file name="CasaBlancaAerialNight.jpg" server="ftp.jacovip.com" local="3601164424" remote="326240088703205244" Dst="-1" /><file name="SunsetSwim.jpg" server="ftp.jacovip.com" local="3601164377" remote="326240088703205244" Dst="-1" /><file name="VIP-Chef-Sushi.jpg" server="ftp.jacovip.com" local="3621625179" remote="3621632520" Dst="-1" /><file name="ChefServiceSushi.jpg" server="ftp.jacovip.com" local="3621625138" remote="3621632520" Dst="-1" /><file name="CasaBlanca-Aerial1.jpg" server="ftp.jacovip.com" local="3621625866" remote="3621633180" Dst="-1" /><file name="CasaBlanca-Aerial2.jpg" server="ftp.jacovip.com" local="3621625878" remote="3621633180" Dst="-1" /></dwsync>